group_stratifier/__init__.py
group_stratifier/main.py
group_stratifier/util.py
group_stratifier-0.1.1.dist-info/METADATA
group_stratifier-0.1.1.dist-info/WHEEL
group_stratifier-0.1.1.dist-info/top_level.txt
group_stratifier-0.1.1.dist-info/RECORD
