Metadata-Version: 2.1
Name: group-stratifier
Version: 0.1.1
Summary: UNKNOWN
Home-page: UNKNOWN
Author: Yigit Ozen
Author-email: UNKNOWN
License: UNKNOWN
Platform: UNKNOWN
Requires-Dist: numpy (>=1.17.0)
Requires-Dist: pyeasyga
